[
  {
    "id": "Salesforce.FitResultsSpringLoaderPlugin",
    "description": "Plugin for creating custom spinnaker stage to perfom deployment of machine image, fetch the fit test run ID and display the FIT results in a single stage",
    "provider": "https://www.salesforce.com",
    "releases": [
        {
            "version": "0.0.13",
            "date": "2021-07-15T04:48:00.751471Z",
            "requires": "orca>=0.0.0,deck>=0.0.0",
            "sha512sum": "5ff3934ed9e43e4117f0848cfac182631102765a663a77bef005c9d89bf0aa06aeb1100b18bdd4b250a59a7368c1841be2808bf0e9984c1807ba060004cf64aa",
            "preferred": false,
            "url": "https://github.com/EshwarNK/SingleStageFitResults/releases/download/0.0.13/SingleStageFitResults-0.0.13.zip"
        }
    ]
  }
]























